cythonarrays/__init__.py
cythonarrays/_version.py
cythonarrays/array_descriptors.py
cythonarrays/array_properties.py
cythonarrays/array_shapes.c
cythonarrays/array_shapes.cp311-win_amd64.pyd
cythonarrays/array_shapes.pxd
cythonarrays/array_shapes.pyx
cythonarrays/array_shapes.pyxbld
cythonarrays/build_config.py
cythonarrays/configure_logger.py
cythonarrays/make_cython_extensions.py
cythonarrays/numpy_types.pxd
cythonarrays/numpy_types.py
cythonarrays/tests/__init__.py
cythonarrays/tests/example_cython.c
cythonarrays/tests/example_cython.cp311-win_amd64.pyd
cythonarrays/tests/example_cython.pxd
cythonarrays/tests/example_cython.pyx
cythonarrays/tests/example_cython.pyxbld
cythonarrays/tests/example_python.py
cythonarrays/tests/module_with_logging.py
cythonarrays/tests/simple_cython.c
cythonarrays/tests/simple_cython.cp311-win_amd64.pyd
cythonarrays/tests/simple_cython.pxd
cythonarrays/tests/simple_cython.pyx
cythonarrays/tests/simple_cython.pyxbld
cythonarrays/tests/simple_python.py
cythonarrays/tests/test_cythonarray.py
cythonarrays/tests/test_logger.py
cythonarrays/tests/test_makeext.py
cythonarrays/tests/examplepackage/__init__.py
cythonarrays/tests/examplepackage/example2_cython.pxd
cythonarrays/tests/examplepackage/example2_cython.pyx
cythonarrays/tests/examplepackage/example2_cython.pyxbld
cythonarrays-1.6.4.dist-info/METADATA
cythonarrays-1.6.4.dist-info/WHEEL
cythonarrays-1.6.4.dist-info/top_level.txt
cythonarrays-1.6.4.dist-info/RECORD
