Metadata-Version: 2.4
Name: cythonarrays
Version: 1.6.4
Summary: cython cdef-class to facilitate numpy-arrays as attributes
Maintainer-email: Max Bohnet <bohnet@ggr-planung.de>
License: GPL-2.0 AND BSD-3-Clause
Project-URL: Documentation, https://maxbo.github.io/cythonarrays/
Project-URL: Source, https://github.com/MaxBo/cythonarrays/
Project-URL: Issue Tracker, https://github.com/MaxBo/cythonarrays/issues
Classifier: Development Status :: 5 - Production/Stable
Classifier: Programming Language :: Cython
Classifier: Programming Language :: Python
Classifier: Programming Language :: Python :: 3
Classifier: Programming Language :: Python :: 3.9
Classifier: Programming Language :: Python :: 3.10
Classifier: Programming Language :: Python :: 3.11
Classifier: Programming Language :: Python :: 3.12
Classifier: Programming Language :: Python :: 3.13
Classifier: Topic :: Software Development :: Libraries
Requires-Python: >=3.9
Requires-Dist: cython
Requires-Dist: numpy
Requires-Dist: xarray
Requires-Dist: h5netcdf>=1.6
Requires-Dist: setuptools
Provides-Extra: test
Requires-Dist: pytest; extra == "test"
